{
  "benefits": {
    "bullets": [
      "Usage-based architecture aligned to production demand",
      "Transparent plan limits and API-driven metering",
      "Operational path from pilot volume to scaled deployment",
      "Automate client-ready weekly recaps.",
      "Deliver consistent brand-aligned updates across accounts."
    ],
    "title": "Commercial outcomes"
  },
  "canonicalUrl": "/use-cases/marketing-agency/weekly-metrics-video/video-api-pricing",
  "cluster": "buyer-intent",
  "cta": {
    "body": "Start a paid trial and ship a deterministic weekly metrics video workflow for Marketing agencies.",
    "primary": {
      "href": "/dashboard",
      "label": "Estimate paid plan"
    },
    "title": "Launch weekly metrics video with video api pricing"
  },
  "faq": [
    {
      "a": "Yes. Templates are versioned and the same input produces the same output.",
      "q": "Is the output deterministic? (video api pricing)"
    },
    {
      "a": "Use the webhook URL to embed in-app or send via email/portal.",
      "q": "How do I deliver the video? (video api pricing)"
    },
    {
      "a": "Marketing agencies teams use video api pricing to automate weekly metrics video without manual editing bottlenecks.",
      "q": "Why is video api pricing relevant for Marketing agencies teams?"
    }
  ],
  "hero": {
    "eyebrow": "High-intent workflow",
    "headline": "Weekly metrics video video api pricing for Marketing agencies",
    "primaryCta": {
      "href": "/dashboard",
      "label": "Estimate paid plan"
    },
    "secondaryCta": {
      "href": "/pricing",
      "label": "View pricing"
    },
    "subheadline": "Estimate spend and implementation scope before procurement. Built for Marketing agencies teams running weekly metrics video.",
    "supportLine": "Operational fit: Spend and Leads with a weekly report is ready."
  },
  "howItWorks": {
    "steps": [
      {
        "body": "Map weekly metrics video requirements to video api pricing buying criteria.",
        "title": "Qualify workflow"
      },
      {
        "body": "Use a versioned template such as weekly-summary-v1.",
        "title": "Pick a template"
      },
      {
        "body": "POST metrics JSON to /render with your API key.",
        "title": "Send data"
      },
      {
        "body": "Launch a paid trial workflow, validate output quality, then expand to recurring automation.",
        "title": "Pilot and scale"
      }
    ],
    "title": "Implementation sequence"
  },
  "id": "buyer_intent.marketing-agency.weekly-metrics-video.video-api-pricing",
  "intentSlug": "video-api-pricing",
  "io": {
    "inputJsonExample": {
      "brand": "marketing-agency",
      "data": {
        "highlight": "clients",
        "industry": "marketing-agency",
        "kpis": {
          "cpl": 20.4,
          "leads": 612,
          "roas": 3.1,
          "spend": 12450
        },
        "narrative": "Marketing agencies weekly metrics video execution update",
        "trigger": "weekly-report",
        "workflow": "weekly-metrics-video"
      },
      "intent": "video-api-pricing",
      "template": "weekly-summary-v1"
    },
    "inputTitle": "Input (commercially-ready JSON)",
    "outputBullets": [
      "45-60s MP4 video",
      "Brand colors, logo, and typography applied",
      "Charts rendered from provided KPIs",
      "Delivery targets: email, client portal, Slack Connect for marketing agencies stakeholders."
    ],
    "outputTitle": "Output (production MP4 + webhook)"
  },
  "lastUpdated": "2026-02-20",
  "metaDescription": "Compare video api pricing options for Marketing agencies. Run weekly metrics video with deterministic templates, webhooks, and paid-trial readiness.",
  "metaTitle": "Video Api Pricing for Marketing agencies Weekly metrics video | Rendivia",
  "problem": {
    "bullets": [
      "Teams struggle to model cost when renders are variable.",
      "Budget owners need predictable unit economics before rollout.",
      "Manual workflows hide real operating cost and labor overhead.",
      "Client reporting is repetitive and time-consuming."
    ],
    "title": "Why Marketing agencies buyers look for video api pricing"
  },
  "related": [
    {
      "href": "/use-cases/marketing-agency/weekly-metrics-video/video-api-software",
      "label": "Weekly metrics video video api software for Marketing agencies"
    },
    {
      "href": "/use-cases/marketing-agency/weekly-metrics-video/video-automation-service",
      "label": "Weekly metrics video video automation service for Marketing agencies"
    },
    {
      "href": "/use-cases/marketing-agency/monthly-metrics-video/video-api-pricing",
      "label": "Monthly metrics video video api pricing for Marketing agencies"
    },
    {
      "href": "/use-cases/marketing-agency/quarterly-qbr-video/video-api-pricing",
      "label": "Quarterly business review (QBR) video video api pricing for Marketing agencies"
    },
    {
      "href": "/use-cases/marketing-agency/investor-update-video/video-api-pricing",
      "label": "Investor update video video api pricing for Marketing agencies"
    },
    {
      "href": "/use-cases/saas/weekly-metrics-video/video-api-pricing",
      "label": "Weekly metrics video video api pricing for SaaS"
    },
    {
      "href": "/use-cases/fintech/weekly-metrics-video/video-api-pricing",
      "label": "Weekly metrics video video api pricing for Fintech"
    },
    {
      "href": "/use-cases/ecommerce/weekly-metrics-video/video-api-pricing",
      "label": "Weekly metrics video video api pricing for E-commerce"
    }
  ],
  "solution": {
    "bullets": [
      "Model projected render volume by workflow and account segment.",
      "Map template complexity to throughput and output duration.",
      "Track webhook completion to close usage and billing loops.",
      "Use weekly-summary-v1 to keep output deterministic across Marketing agencies workflows."
    ],
    "title": "Execution plan for weekly metrics video (video api pricing)"
  },
  "title": "Weekly metrics video video api pricing for Marketing agencies",
  "type": "buyer_intent",
  "version": 1
}
